extasy.coco-0.3.2-py2.7-nspkg.pth
coco/_version.py
coco/coco.py
extasy.coco-0.3.2.data/scripts/pyCoCo
extasy.coco-0.3.2.dist-info/DESCRIPTION.rst
extasy.coco-0.3.2.dist-info/METADATA
extasy.coco-0.3.2.dist-info/metadata.json
extasy.coco-0.3.2.dist-info/namespace_packages.txt
extasy.coco-0.3.2.dist-info/RECORD
extasy.coco-0.3.2.dist-info/top_level.txt
extasy.coco-0.3.2.dist-info/WHEEL
