Metadata-Version: 2.0
Name: extasy.coco
Version: 0.3.2
Summary: EXTASY Project - CoCo
Home-page: https://bitbucket.org/extasy-project/extasy-project
Author: The EXTASY Project
Author-email: charles.laughton@nottingham.ac.uk
License: BSD
Download-URL: https://bitbucket.org/extasy-project/coco/get/0.3.2.tar.gz
Platform: UNKNOWN
Classifier: Development Status :: 5 - Production/Stable
Classifier: Intended Audience :: Science/Research
Classifier: Environment :: Console
Classifier: License :: OSI Approved :: MIT License
Classifier: Programming Language :: Python
Classifier: Programming Language :: Python :: 2
Classifier: Programming Language :: Python :: 2.7
Classifier: Programming Language :: Python :: 3
Classifier: Programming Language :: Python :: 3.4
Classifier: Programming Language :: Python :: 3.5
Classifier: Topic :: Scientific/Engineering
Classifier: Operating System :: MacOS :: MacOS X
Classifier: Operating System :: POSIX
Classifier: Operating System :: Unix
Requires-Dist: numpy
Requires-Dist: scipy
Requires-Dist: pypcazip (>=2.0.0)
Requires-Dist: scikit-image
Requires-Dist: mdtraj
